{
  "entity.wraith_death": {
    "category": "entity",
    "subtitle": "entity.wraith_death.sub",
    "sounds": [
      {
        "name": "krayscandles:entity/wraith_death",
        "stream": true
      }
    ]
  },
  "entity.wraith_hurt": {
    "category": "entity",
    "subtitle": "entity.wraith_hurt.sub",
    "sounds": [
      {
        "name": "krayscandles:entity/wraith_hurt",
        "stream": true
      }
    ]
  },
  "entity.wraith_ambient": {
    "category": "entity",
    "subtitle": "entity.wraith_ambient.sub",
    "sounds": [
      {
        "name": "krayscandles:entity/wraith_ambient",
        "stream": true
      }
    ]
  },
  "entity.wraith_damned_death": {
    "category": "entity",
    "subtitle": "entity.wraith_damned_death.sub",
    "sounds": [
      {
        "name": "krayscandles:entity/wraith_damned_death",
        "stream": true
      }
    ]
  },
  "entity.wraith_damned_hurt": {
    "category": "entity",
    "subtitle": "entity.wraith_damned_hurt.sub",
    "sounds": [
      {
        "name": "krayscandles:entity/wraith_damned_hurt",
        "stream": true
      }
    ]
  },
  "entity.wraith_damned_ambient": {
    "category": "entity",
    "subtitle": "entity.wraith_damned_ambient.sub",
    "sounds": [
      {
        "name": "krayscandles:entity/wraith_damned_ambient",
        "stream": true
      }
    ]
  },
  "entity.vampire_ambient": {
    "category": "entity",
    "subtitle": "entity.vampire_ambient.sub",
    "sounds": [
      {
        "name": "krayscandles:entity/vampire_ambient",
        "stream": true
      }
    ]
  },
  "entity.vampire_hurt": {
    "category": "entity",
    "subtitle": "entity.vampire_hurt.sub",
    "sounds": [
      {
        "name": "krayscandles:entity/vampire_hurt",
        "stream": true
      }
    ]
  },
  "entity.vampire_death": {
    "category": "entity",
    "subtitle": "entity.vampire_death.sub",
    "sounds": [
      {
        "name": "krayscandles:entity/vampire_death",
        "stream": true
      }
    ]
  },
  "entity.vampire_vanish": {
    "category": "entity",
    "subtitle": "entity.vampire_vanish.sub",
    "sounds": [
      {
        "name": "krayscandles:entity/vampire_vanish",
        "stream": true
      }
    ]
  },
  "entity.vampire_weakened": {
    "category": "entity",
    "subtitle": "entity.vampire_weakened.sub",
    "sounds": [
      {
        "name": "krayscandles:entity/vampire_weakened",
        "stream": true
      }
    ]
  },
  "block.wraith_ritual": {
    "category": "block",
    "subtitle": "block.wraith_ritual.sub",
    "sounds": [
      {
        "name": "krayscandles:block/wraith_ritual",
        "stream": true
      }
    ]
  },
  "block.wand_ritual": {
    "category": "block",
    "subtitle": "block.wand_ritual.sub",
    "sounds": [
      {
        "name": "krayscandles:block/wand_ritual",
        "stream": true
      }
    ]
  },
  "block.rune_ritual": {
    "category": "block",
    "subtitle": "block.rune_ritual.sub",
    "sounds": [
      {
        "name": "krayscandles:block/rune_ritual",
        "stream": true
      }
    ]
  },
  "disc.music_disc_chunk": {
    "category": "disc",
    "subtitle": "Kray - chunk",
    "sounds": [
      {
        "name": "krayscandles:disc/music_disc_chunk",
        "stream": true
      }
    ]
  }
}
